{
    "geometry": {
        "coordinates": [
            [
                [
                    115.70424244499239,
                    39.798583
                ],
                [
                    115.70822377753223,
                    39.81278905256232
                ],
                [
                    115.70831589945075,
                    39.812773413820295
                ],
                [
                    115.74546747699472,
                    39.94488204421638
                ],
                [
                    115.74618090229909,
                    39.94476102493825
                ],
                [
                    115.76956215719851,
                    40.028769
                ],
                [
                    115.8276449757191,
                    40.028769
                ],
                [
                    116.06813560619761,
                    40.028769
                ],
                [
                    116.1598718320368,
                    40.028769
                ],
                [
                    116.14983329372414,
                    39.994104634641545
                ],
                [
                    116.1063461199482,
                    39.84333001542265
                ],
                [
                    116.1060472350656,
                    39.843380358864295
                ],
                [
                    116.09316297594489,
                    39.798583
                ],
                [
                    115.79190626393198,
                    39.798583
                ],
                [
                    115.70432527251106,
                    39.798583
                ],
                [
                    115.70424244499239,
                    39.798583
                ]
            ]
        ],
        "type": "Polygon"
    },
    "properties": {
        "strip_id": "6525259"
    }
}