{
    "geometry": {
        "type": "Polygon",
        "coordinates": [
            [
                [
                    81.85318607,
                    35.709753662368435
                ],
                [
                    81.86986058517178,
                    35.70678112606445
                ],
                [
                    81.85318607,
                    35.645067487442006
                ],
                [
                    81.85318607,
                    35.709753662368435
                ]
            ]
        ]
    },
    "properties": {
        "strip_id": "3775194"
    }
}