{
    "geometry": {
        "type": "Polygon",
        "coordinates": [
            [
                [
                    83.12991564499728,
                    35.41914938
                ],
                [
                    83.12846448972677,
                    35.42477874214343
                ],
                [
                    83.20113104,
                    35.43725797362071
                ],
                [
                    83.20113104,
                    35.41914938
                ],
                [
                    83.12991564499728,
                    35.41914938
                ]
            ]
        ]
    },
    "properties": {
        "strip_id": "3769456"
    }
}